vsup/__init__.py
vsup/quantization.py
vsup/transforms.py
vsup/vsup.py
vsup-0.1.0.dist-info/METADATA
vsup-0.1.0.dist-info/WHEEL
vsup-0.1.0.dist-info/RECORD
