Metadata-Version: 2.4
Name: vsup
Version: 0.1.0
Summary: Value-Suppressing Uncertainty Palettes for Python
Project-URL: Homepage, https://github.com/JohnGoertz/vsup
Project-URL: Bug Tracker, https://github.com/JohnGoertz/vsup/issues
Author-email: John Goertz <johngoertz@gmail.com>
Classifier: Development Status :: 3 - Alpha
Classifier: Intended Audience :: Science/Research
Classifier: License :: OSI Approved :: MIT License
Classifier: Programming Language :: Python :: 3
Classifier: Programming Language :: Python :: 3.8
Classifier: Programming Language :: Python :: 3.9
Classifier: Programming Language :: Python :: 3.10
Classifier: Programming Language :: Python :: 3.11
Classifier: Programming Language :: Python :: 3.12
Classifier: Programming Language :: Python :: 3.13
Classifier: Topic :: Scientific/Engineering :: Visualization
Requires-Python: >=3.8
Requires-Dist: matplotlib>=3.7.0
Requires-Dist: numpy>=1.24.0
Requires-Dist: scikit-image
Requires-Dist: seaborn>=0.12.0
